{
  "basics": {
    "name": "Lambert Leong",
    "label": "Student & Researcher",
    "picture": "https://LambertLeong.github.io/images/profile2d.jpg ",
    "email": "lambert3@hawaii.edu",
    "phone": "808-429-2576",
    "website": "https://LambertLeong.github.io",
    "summary": "I am studying Information and Computer Sciences at the University of Hawaii, Manoa and expect to graduate in 2018.  I also recieved my B.S. in biology with a minor in chemistry from the University of Oregon.  After receiving my degree in computer science, I hope to continue to work in the bio-tech and bio-medical fields.",
    "location": {
      "address": "",
      "postalCode": "96822",
      "city": "Honolulu",
      "countryCode": "USA",
      "region": "Hawaii"
    },
    "profiles": [
      {
        "network": "github",
        "username": "LambertLeong",
        "url": "http://github.com/LambertLeong"
      },
      {
        "network": "linkedin",
        "username": "Lambert Leong",
        "url": "https://www.linkedin.com/in/lambert-leong-0bba23a4"
      },

    ]
  },
  "interests": [
    {
      "name": "bioinformatics",
      "keywords": [
      ]
    },
    {
      "name": "databases",
      "keywords": [
      ]
    },
    {
      "name": "web development",
      "keywords": [
      ]
    }
  ],
  "skills": [
    {
      "name": "Languages and Frameworks",
      "level": "",
      "keywords": [
        "C",
        "C++",
        "Java",
        "Javascript",
      ]
    },
    {
      "name": "Toolsets/OS",
      "level": "",
      "keywords": [
        "Windows",
        "Git/GitHub",
        "g++"
      ]
    }
  ],
  "education": [
    {
      "institution": "University of Hawaii, Honolulu, HI",
      "area": "Computer Science",
      "studyType": "",
      "startDate": "2015-08-24",
      "endDate": "Present",
      "gpa": "",
      "courses": [
      ]
    },
    {
      "institution": "University of Oregon, Eugene, OR",
      "area": "Biology, minor,chemistry",
      "studyType": "B.S.",
      "startDate": "2010-09-24",
      "endDate": "2014-06-14",
      "gpa": "",
      "courses": [
      ]
    }
  ],
  "work": [
    {
      "company": "Eyegenix LLC",
      "position": "Researcher",
      "website": "http://www.eyegenix.com/",
      "startDate": "2015-08-03",
      "endDate": "Present",
      "summary": "Cell & Tissue Culture, Manufacturing",
      "highlights": [
        "Biocompatibility testing/assays of manufactured products",
        "Maintainging human cell lines",
        "Aseptic technique",
        "Electrophorisis",
        "Polymer formulation and manufacturing",
        "Quality control testing",
        "Data anaylsis",
      ]
    },
    {
      "company": "University of Oregon Student Recreation Center",
      "position": "Fitness Attendant",
      "website": "http://uorec.uoregon.edu",
      "startDate": "2013",
      "endDate": "2014",
      "summary": "",
      "highlights": [
        "Custormer service",
      ]
    },
    {
      "company": "The Queen's Medical Center",
      "position": "Pathology Student Trainee",
      "website": "",
      "startDate": "2011",
      "endDate": "2012",
      "summary": "Research intern, two summers",
      "highlights": [
        "Genomic anaylizer validation",
        "DNA extraction",
        "Laser microdissection",
        "Immunohistochemistry",
        "Proficient with a microscope",
        "Assisted with autopsies",
        "Data anaylsis",
        "Vitural microscopy"
      ]
    }
  ],
  "volunteer": [
    {
      "organization": "Queen's Medical Center",
      "website": "",
      "position": "Pathology Volunteer",
      "startDate": "2016-01-01",
      "endDate": "Present",
      "summary": "Volunteer research assistant",
      "highlights": [
        "Autopsy observation",
        "Specimen slide filing"
      ]
    },
  ],
  "awards": [
    {
      "title": "3D Studio Art",
      "date": "",
      "awarder": "`Iolani School",
      "summary": ""
    },
  ],
  "references": [
    {
      "name": "Available upon request",
      "reference": ""
    }
  ]
}
